LanguageDetection/LanguageDetection.csv
LanguageDetection/LanguageDetection.py
LanguageDetection/__init__.py
LanguageDetection-0.1.3.dist-info/LICENSE
LanguageDetection-0.1.3.dist-info/METADATA
LanguageDetection-0.1.3.dist-info/WHEEL
LanguageDetection-0.1.3.dist-info/top_level.txt
LanguageDetection-0.1.3.dist-info/RECORD
