Metadata-Version: 2.1
Name: LanguageDetection
Version: 0.1.3
Summary: For Language Detection
Author: Mayuresh Choudhary
Author-email: mayureshchoudhary22@gmail.com
Classifier: Programming Language :: Python :: 3
Classifier: License :: OSI Approved :: MIT License
Classifier: Operating System :: OS Independent
Requires-Python: >=3.7
License-File: LICENSE
